pyatmosphere/__init__.py
pyatmosphere/channels.py
pyatmosphere/gpu.py
pyatmosphere/grids.py
pyatmosphere/measures.py
pyatmosphere/pathes.py
pyatmosphere/phase_screens.py
pyatmosphere/pupils.py
pyatmosphere/sources.py
pyatmosphere/utils.py
pyatmosphere/simulations/__init__.py
pyatmosphere/simulations/beam.py
pyatmosphere/simulations/measure.py
pyatmosphere/simulations/pdt.py
pyatmosphere/simulations/result.py
pyatmosphere/simulations/si.py
pyatmosphere/simulations/simulation.py
pyatmosphere/simulations/structure_function.py
pyatmosphere/simulations/wind.py
pyatmosphere/theory/__init__.py
pyatmosphere/theory/models.py
pyatmosphere/theory/sources.py
pyatmosphere/theory/vacuum.py
pyatmosphere/theory/atmosphere/__init__.py
pyatmosphere/theory/atmosphere/beam_wandering.py
pyatmosphere/theory/atmosphere/gamma2.py
pyatmosphere/theory/atmosphere/long_term.py
pyatmosphere/theory/atmosphere/short_term.py
pyatmosphere/theory/atmosphere/si.py
pyatmosphere/theory/pdt/__init__.py
pyatmosphere/theory/pdt/elliptic_beam.py
pyatmosphere/theory/pdt/pdt.py
pyatmosphere/theory/phase_screens/__subharmonics.py
pyatmosphere/theory/phase_screens/sf.py
pyAtmosphere-0.0.1.dist-info/LICENSE
pyAtmosphere-0.0.1.dist-info/METADATA
pyAtmosphere-0.0.1.dist-info/WHEEL
pyAtmosphere-0.0.1.dist-info/top_level.txt
pyAtmosphere-0.0.1.dist-info/RECORD
