Metadata-Version: 2.1
Name: pyAtmosphere
Version: 0.0.1
Summary: Physics-based simulation of light propagation in turbulent atmosphere
Author-email: Mykyta Yurin <phys@yurin.space>
License: GNU GENERAL PUBLIC LICENSE
Project-URL: source, https://github.com/NYurin/pyAtmosphere
Classifier: Development Status :: 3 - Alpha
Classifier: Intended Audience :: Science/Research
Classifier: Intended Audience :: Developers
Classifier: Intended Audience :: Education
Classifier: Intended Audience :: Information Technology
Classifier: Intended Audience :: Science/Research
Classifier: Intended Audience :: Telecommunications Industry
Classifier: Programming Language :: Python
Classifier: Programming Language :: Python :: 3
Classifier: Programming Language :: Python :: 3.7
Classifier: Programming Language :: Python :: 3.8
Classifier: Programming Language :: Python :: 3.9
Classifier: Programming Language :: Python :: 3.10
Classifier: Topic :: Software Development :: Libraries
Classifier: Topic :: Scientific/Engineering
Classifier: Topic :: Scientific/Engineering :: Astronomy
Classifier: Topic :: Scientific/Engineering :: Atmospheric Science
Classifier: Topic :: Scientific/Engineering :: Physics
Classifier: Topic :: Education
Classifier: Topic :: Security
Classifier: Topic :: Security :: Cryptography
Classifier: License :: OSI Approved :: GNU General Public License v3 (GPLv3)
Classifier: Operating System :: OS Independent
Classifier: Operating System :: Microsoft :: Windows
Classifier: Operating System :: POSIX :: Linux
Classifier: Operating System :: POSIX
Classifier: Operating System :: Unix
Classifier: Operating System :: MacOS
Classifier: Environment :: GPU
Classifier: Environment :: GPU :: NVIDIA CUDA
Requires-Python: >=3.7
License-File: LICENSE
Requires-Dist: numpy
Requires-Dist: pandas
Requires-Dist: scipy
Requires-Dist: matplotlib
Requires-Dist: typing-extensions ; python_version < "3.8"
Provides-Extra: doc
Requires-Dist: sphinx ; extra == 'doc'
Provides-Extra: jupyter
Requires-Dist: jupyter-ui-poll ; extra == 'jupyter'
